verbose_csrf_middleware/__init__.py
verbose_csrf_middleware/scmversion.py
verbose_csrf_middleware/tests.py
verbose_csrf_middleware-6.0.0.dist-info/licenses/LICENSE
verbose_csrf_middleware-6.0.0.dist-info/METADATA
verbose_csrf_middleware-6.0.0.dist-info/WHEEL
verbose_csrf_middleware-6.0.0.dist-info/top_level.txt
verbose_csrf_middleware-6.0.0.dist-info/RECORD
