Metadata-Version: 2.4
Name: verbose_csrf_middleware
Version: 6.0.0
Summary: Verbatim copy of Django's CSRF middleware, but with more verbose error messages.
Author-email: "Bugsink B.V." <info@bugsink.com>
License-Expression: BSD-3-Clause
Project-URL: homepage, https://www.bugsink.com/docs/verbose_csrf_middleware/
Project-URL: documentation, https://www.bugsink.com/docs/verbose_csrf_middleware/
Project-URL: issues, https://github.com/bugsink/verbose_csrf_middleware/issues
Project-URL: repository, https://github.com/bugsink/verbose_csrf_middleware
Classifier: Framework :: Django
Classifier: Programming Language :: Python :: 3
Requires-Python: >=3.12
License-File: LICENSE
Dynamic: license-file
